application/__init__.py
application/main.py
application/models.py
application/teste_lib.py
calc_lib/__init__.py
calc_lib/funcoes.py
calc_lib_jhonin-0.1.0.dist-info/METADATA
calc_lib_jhonin-0.1.0.dist-info/WHEEL
calc_lib_jhonin-0.1.0.dist-info/entry_points.txt
calc_lib_jhonin-0.1.0.dist-info/top_level.txt
calc_lib_jhonin-0.1.0.dist-info/RECORD
