Metadata-Version: 2.4
Name: calc_lib_jhonin
Version: 0.1.0
Summary: A simple calculator API using FastAPI
Author: Jonathan Castro Silva
License: MIT
Requires-Python: >=3.9
Requires-Dist: fastapi==0.95.2
Requires-Dist: pydantic==1.10.7
Requires-Dist: uvicorn==0.22.0
Dynamic: author
Dynamic: license
Dynamic: requires-dist
Dynamic: requires-python
Dynamic: summary
